examples/__init__.py
sodo/__init__.py
sodo/default_settings.py
sodo/filter/__init__.py
sodo/filter/redis.py
sodo/hook/__init__.py
sodo/pipeline/__init__.py
sodo/pipeline/elasticsearch.py
sodo/pipeline/kafka.py
sodo/queue/__init__.py
sodo/queue/redis.py
sodo/scheduler/__init__.py
sodo/scheduler/redis.py
sodo/spider/__init__.py
sodo/spider/kafka.py
sodo/utils/__init__.py
sodo/utils/connection.py
sodo/utils/decorator.py
sodo/utils/net.py
sodo/utils/serialize.py
sodo/utils/string.py
SoDo-1.0.1.dist-info/LICENSE
SoDo-1.0.1.dist-info/METADATA
SoDo-1.0.1.dist-info/WHEEL
SoDo-1.0.1.dist-info/top_level.txt
SoDo-1.0.1.dist-info/RECORD
