Metadata-Version: 2.1
Name: SoDo
Version: 1.0.1
Summary: Redis-based  scheduler and Message queue Spider for Scrapy,  Provide more flexible and practical ways for Scrapy
Home-page: https://github.com/ycvbcvfu/sodo
Author: ryan
Author-email: legotime@qq.com
Maintainer: ryan
License: MIT License
Platform: UNKNOWN
Requires-Dist: Scrapy
Requires-Dist: kafka
Requires-Dist: redis
